shopcloud_datalake/__init__.py
shopcloud_datalake/__main__.py
shopcloud_datalake/cli.py
shopcloud_datalake/config.py
shopcloud_datalake/erps.py
shopcloud_datalake/exceptions.py
shopcloud_datalake/helpers.py
shopcloud_datalake/managers.py
shopcloud_datalake/running.py
shopcloud_datalake/steps.py
shopcloud_datalake/storages.py
shopcloud_datalake/tables.py
shopcloud_datalake/warehouses.py
shopcloud_datalake-1.5.0.data/scripts/datalake
tests/__init__.py
tests/test_cli.py
tests/test_erps.py
tests/test_exceptions.py
tests/test_helpers.py
tests/test_managers.py
tests/test_storages.py
tests/test_tables.py
tests/test_warehouses.py
shopcloud_datalake-1.5.0.dist-info/LICENSE
shopcloud_datalake-1.5.0.dist-info/METADATA
shopcloud_datalake-1.5.0.dist-info/WHEEL
shopcloud_datalake-1.5.0.dist-info/top_level.txt
shopcloud_datalake-1.5.0.dist-info/RECORD
