Metadata-Version: 2.1
Name: shopcloud-datalake
Version: 1.5.0
Summary: CLI tool for datalake operation
Home-page: https://github.com/Talk-Point/shopcloud-datalake-cli
Author: Konstantin Stoldt
Author-email: konstantin.stoldt@talk-point.de
License: MIT
Keywords: CLI
License-File: LICENSE
Requires-Dist: pyyaml
Requires-Dist: requests
Requires-Dist: pytest
Requires-Dist: shopcloud-secrethub >=2.12.0
Requires-Dist: pre-commit
Requires-Dist: google-cloud-storage
Requires-Dist: google-cloud-bigquery
Requires-Dist: pandas
Requires-Dist: tqdm
Requires-Dist: pyarrow
Requires-Dist: fastparquet
Requires-Dist: prompt-toolkit
